patternlocal/__init__.py
patternlocal/exceptions.py
patternlocal/config/__init__.py
patternlocal/config/config.py
patternlocal/config/validation.py
patternlocal/core/explainer.py
patternlocal/core/strategies.py
patternlocal/simplification/__init__.py
patternlocal/simplification/base.py
patternlocal/simplification/lowrank.py
patternlocal/simplification/no_simplification.py
patternlocal/simplification/registry.py
patternlocal/simplification/superpixel.py
patternlocal/solvers/__init__.py
patternlocal/solvers/base.py
patternlocal/solvers/global_covariance.py
patternlocal/solvers/lasso.py
patternlocal/solvers/local_base.py
patternlocal/solvers/local_covariance.py
patternlocal/solvers/no_solver.py
patternlocal/solvers/registry.py
patternlocal/solvers/ridge.py
patternlocal/tests/conftest.py
patternlocal/tests/test_basic.py
patternlocal/tests/test_unified_api.py
patternlocal/utils/__init__.py
patternlocal/utils/distance.py
patternlocal/utils/kernels.py
patternlocal/utils/parallel.py
patternlocal/utils/projection.py
patternlocal/utils/registry.py
patternlocal/utils/superpixel.py
patternlocal-1.0.1.dist-info/licenses/LICENSE
patternlocal-1.0.1.dist-info/METADATA
patternlocal-1.0.1.dist-info/WHEEL
patternlocal-1.0.1.dist-info/top_level.txt
patternlocal-1.0.1.dist-info/RECORD
