Metadata-Version: 2.4
Name: patternlocal
Version: 1.0.1
Summary: PatternLocal explanations for machine learning models
Home-page: https://github.com/gjoelbye/PatternLocal
Author: Anders Gjølbye
Author-email: Anders Gjølbye Madsen <agjma@dtu.dk>
License: MIT
Project-URL: Homepage, https://github.com/gjoelbye/PatternLocal
Project-URL: Documentation, https://github.com/gjoelbye/PatternLocal
Project-URL: Repository, https://github.com/gjoelbye/PatternLocal
Project-URL: Paper, https://arxiv.org/abs/2505.11210
Keywords: explainable-ai,machine-learning,causality,lime,interpretability,supressor-variables,pattern
Classifier: Development Status :: 4 - Beta
Classifier: Intended Audience :: Developers
Classifier: Intended Audience :: Science/Research
Classifier: Operating System :: OS Independent
Classifier: Programming Language :: Python :: 3
Classifier: Programming Language :: Python :: 3.8
Classifier: Programming Language :: Python :: 3.9
Classifier: Programming Language :: Python :: 3.10
Classifier: Programming Language :: Python :: 3.11
Classifier: Programming Language :: Python :: 3.12
Classifier: Programming Language :: Python :: 3.13
Classifier: Topic :: Scientific/Engineering :: Artificial Intelligence
Classifier: Topic :: Software Development :: Libraries :: Python Modules
Requires-Python: >=3.7
License-File: LICENSE
Requires-Dist: numpy>=1.19.0
Requires-Dist: scikit-learn>=1.0.0
Requires-Dist: scipy>=1.7.0
Requires-Dist: lime>=0.2.0
Requires-Dist: scikit-image>=0.18.0
Provides-Extra: dev
Requires-Dist: pytest>=6.0; extra == "dev"
Requires-Dist: pytest-cov>=2.0; extra == "dev"
Requires-Dist: black>=21.0; extra == "dev"
Requires-Dist: isort>=5.0; extra == "dev"
Requires-Dist: flake8>=3.8; extra == "dev"
Requires-Dist: mypy>=0.900; extra == "dev"
Requires-Dist: pre-commit>=2.0; extra == "dev"
Provides-Extra: examples
Requires-Dist: matplotlib>=3.3.0; extra == "examples"
Requires-Dist: jupyter>=1.0.0; extra == "examples"
Requires-Dist: seaborn>=0.11.0; extra == "examples"
Dynamic: author
Dynamic: home-page
Dynamic: license-file
Dynamic: requires-python
